pyknife/__init__.py
pyknife/audiofile/__init__.py
pyknife/aws/__init__.py
pyknife/console/__init__.py
pyknife/dsp/__init__.py
pyknife/dsp/pghi.py
pyknife/file/__init__.py
pyknife/network/__init__.py
pyknife-0.0.3.dist-info/LICENSE
pyknife-0.0.3.dist-info/METADATA
pyknife-0.0.3.dist-info/WHEEL
pyknife-0.0.3.dist-info/top_level.txt
pyknife-0.0.3.dist-info/RECORD
